{
    "stun": {
        "name": "Stun",
        "adjective": "Stunned",
        "icon": "statuses/stunned.svg",
        "debuff": true,
        "duration": [ 1, 3 ],
        "max_stacks": 1,
        "effects": [
            {
                "StatModifier": {
                    "stat": {
                        "Speed": { }
                    },
                    "modifier": "More",
                    "debuff": true
                },
                "value": 1e+200,
                "modifier": "Flat"
            }
        ]
    },
    "stun_lockout": {
        "name": "Stun Lockout",
        "icon": "statuses/stun_immune.svg",
        "debuff": false,
        "duration": 0,
        "max_stacks": 1,
        "effects": [
            {
                "StatModifier": {
                    "stat": {
                        "StatusResistance": {
                            "status_id": "stun"
                        }
                    }
                },
                "value": 100,
                "modifier": "Flat"
            }
        ]
    },
    "chill": {
        "name": "Chill",
        "adjective": "Chilled",
        "icon": "statuses/chilled.svg",
        "debuff": true,
        "duration": 5,
        "max_stacks": 5,
        "effects": [
            {
                "StatModifier": {
                    "stat": {
                        "Speed": { }
                    },
                    "modifier": "Increased",
                    "debuff": true
                },
                "value": 100,
                "modifier": "Percent"
            }
        ]
    }
}